README.md
setup.cfg
setup.py
distributions_zxcvb/Binomialdistribution.py
distributions_zxcvb/Gaussiandistribution.py
distributions_zxcvb/Generaldistribution.py
distributions_zxcvb/__init__.py
distributions_zxcvb.egg-info/PKG-INFO
distributions_zxcvb.egg-info/SOURCES.txt
distributions_zxcvb.egg-info/dependency_links.txt
distributions_zxcvb.egg-info/not-zip-safe
distributions_zxcvb.egg-info/top_level.txt